projexui/__init__.py
projexui/_version.py
projexui/pyi_hook.py
projexui/qt.py
projexui/xanimation.py
projexui/xapplication.py
projexui/xcoloricon.py
projexui/xcolorset.py
projexui/xcommands.py
projexui/xdatatype.py
projexui/xexporter.py
projexui/xfont.py
projexui/xhistorystack.py
projexui/xlogginghandler.py
projexui/xorblookupworker.py
projexui/xorbworker.py
projexui/xpainter.py
projexui/xpalette.py
projexui/xresourcemanager.py
projexui/xscheme.py
projexui/xsettings.py
projexui/xthread.py
projexui/xtimer.py
projexui/xwidgetvalue.py
projexui/completers/__init__.py
projexui/completers/xjoincompleter.py
projexui/completers/xorbcolumncompleter.py
projexui/completers/xorbsearchcompleter.py
projexui/completers/xquerycompleter.py
projexui/configs/__init__.py
projexui/configs/xschemeconfig.py
projexui/configs/xshortcutconfig/__init__.py
projexui/configs/xshortcutconfig/xshortcutconfig.py
projexui/configs/xshortcutconfig/xshortcutwidget.py
projexui/configs/xshortcutconfig/ui/xshortcutwidget.ui
projexui/designer/__init__.py
projexui/designer/build/__init__.py
projexui/designer/build/xactiongroupwidgetplugin.py
projexui/designer/build/xboolcomboboxplugin.py
projexui/designer/build/xcalendarwidgetplugin.py
projexui/designer/build/xchartplugin.py
projexui/designer/build/xcollapsibleloggerwidgetplugin.py
projexui/designer/build/xcolorbuttonplugin.py
projexui/designer/build/xcolortreewidgetplugin.py
projexui/designer/build/xcomboboxplugin.py
projexui/designer/build/xcommenteditplugin.py
projexui/designer/build/xconsoleeditplugin.py
projexui/designer/build/xconsolestatusbarplugin.py
projexui/designer/build/xcurrencyspinboxplugin.py
projexui/designer/build/xdateeditplugin.py
projexui/designer/build/xdatetimeeditplugin.py
projexui/designer/build/xdevtoolswidgetplugin.py
projexui/designer/build/xenumboxplugin.py
projexui/designer/build/xfilepatheditplugin.py
projexui/designer/build/xfindwidgetplugin.py
projexui-2015.0.21.dist-info/DESCRIPTION.rst
projexui-2015.0.21.dist-info/METADATA
projexui-2015.0.21.dist-info/RECORD
projexui-2015.0.21.dist-info/WHEEL
projexui-2015.0.21.dist-info/metadata.json
projexui-2015.0.21.dist-info/top_level.txt
