Metadata-Version: 2.0
Name: projexui
Version: 2015.0.21
Summary: Library of Qt extension widgets.
Home-page: https://github.com/ProjexSoftware/projexui
Author: Eric Hulser
Author-email: eric.hulser@gmail.com
License: LGPL
Platform: UNKNOWN
Requires-Dist: projex
Requires-Dist: xqt
